<?xml version="1.0" encoding="iso-8859-1" ?>
<!DOCTYPE rem:requirementsProject SYSTEM "C:\Program Files\REM 1.2.2\xml\REM_1_2_2.dtd">
<rem:requirementsProject
xmlns:rem="http://rem.lsi.us.es">
<rem:name>PAYME</rem:name>
<rem:c_requirementsSpecification oid = "CRS-0001">
<rem:name>Documento de Requisitos del Sistema</rem:name>
<rem:version>
<rem:major>1</rem:major>
<rem:minor>0</rem:minor>
<rem:date>
<rem:year>2012</rem:year>
<rem:month>9</rem:month>
<rem:day>30</rem:day>
</rem:date>
</rem:version>
<rem:comments>
Ninguno
</rem:comments>
	 <rem:preparedFor organizations = "ORG-0001 "/>
	 <rem:preparedBy organizations = "ORG-0002 "/>
<rem:section
 oid = "SEC-0005">
<rem:name>
Organizacion</rem:name>
<rem:version>
<rem:major>1</rem:major>
<rem:minor>0</rem:minor>
<rem:date>
<rem:year>2012</rem:year>
<rem:month>9</rem:month>
<rem:day>30</rem:day>
</rem:date>
</rem:version>
<rem:authors stakeholders ="STK-0001 STK-0002 "/>
<rem:comments>
Ninguno</rem:comments>
<rem:level>1</rem:level>
<rem:number>1 </rem:number>
<rem:organization
 oid = "ORG-0001">
<rem:name>
PAYME</rem:name>
<rem:version>
<rem:major>1</rem:major>
<rem:minor>0</rem:minor>
<rem:date>
<rem:year>2012</rem:year>
<rem:month>9</rem:month>
<rem:day>30</rem:day>
</rem:date>
</rem:version>
<rem:authors stakeholders ="STK-0001 STK-0002 "/>
<rem:sources stakeholders ="STK-0003 "/>
<rem:comments>
Ninguno</rem:comments>
<rem:address>Cl 45 n 78b 104 </rem:address>
<rem:telephone>555111-11</rem:telephone>
<rem:fax>232222222</rem:fax>
</rem:organization>
<rem:organization
 oid = "ORG-0002">
<rem:name>
Casa de Software - Pascual Bravo</rem:name>
<rem:version>
<rem:major>1</rem:major>
<rem:minor>0</rem:minor>
<rem:date>
<rem:year>2012</rem:year>
<rem:month>9</rem:month>
<rem:day>30</rem:day>
</rem:date>
</rem:version>
<rem:authors stakeholders ="STK-0001 STK-0002 "/>
<rem:comments>
Ninguno</rem:comments>
<rem:address>cl 94 n 23bb 84</rem:address>
<rem:telephone>52222-222</rem:telephone>
<rem:fax>55523244</rem:fax>
</rem:organization>
</rem:section>
<rem:section
 oid = "SEC-0006">
<rem:name>
Participantes</rem:name>
<rem:version>
<rem:major>1</rem:major>
<rem:minor>0</rem:minor>
<rem:date>
<rem:year>2012</rem:year>
<rem:month>9</rem:month>
<rem:day>30</rem:day>
</rem:date>
</rem:version>
<rem:authors stakeholders ="STK-0001 STK-0002 "/>
<rem:comments>
Ninguno</rem:comments>
<rem:level>1</rem:level>
<rem:number>2 </rem:number>
<rem:stakeholder
 oid = "STK-0003">
<rem:name>
Sorey Garcia</rem:name>
<rem:version>
<rem:major>1</rem:major>
<rem:minor>0</rem:minor>
<rem:date>
<rem:year>2012</rem:year>
<rem:month>9</rem:month>
<rem:day>30</rem:day>
</rem:date>
</rem:version>
<rem:comments>
Ninguno</rem:comments>
<rem:stakeholderRole>Dueña</rem:stakeholderRole>
<rem:isCustomer/>
<rem:isUser/>
<rem:worksFor organization = "ORG-0001"/>
</rem:stakeholder>
<rem:stakeholder
 oid = "STK-0001">
<rem:name>
Alexander Restrepo</rem:name>
<rem:version>
<rem:major>1</rem:major>
<rem:minor>0</rem:minor>
<rem:date>
<rem:year>2012</rem:year>
<rem:month>9</rem:month>
<rem:day>30</rem:day>
</rem:date>
</rem:version>
<rem:comments>
Ninguno</rem:comments>
<rem:stakeholderRole>Analista Funcional</rem:stakeholderRole>
<rem:isDeveloper/>
<rem:worksFor organization = "ORG-0002"/>
</rem:stakeholder>
<rem:stakeholder
 oid = "STK-0002">
<rem:name>
Victor Mario</rem:name>
<rem:version>
<rem:major>1</rem:major>
<rem:minor>0</rem:minor>
<rem:date>
<rem:year>2012</rem:year>
<rem:month>9</rem:month>
<rem:day>30</rem:day>
</rem:date>
</rem:version>
<rem:comments>
Ninguno</rem:comments>
<rem:stakeholderRole>Arquitecto </rem:stakeholderRole>
<rem:isDeveloper/>
<rem:worksFor organization = "ORG-0002"/>
</rem:stakeholder>
</rem:section>
<rem:section
 oid = "SEC-0009">
<rem:name>
Contexto</rem:name>
<rem:version>
<rem:major>1</rem:major>
<rem:minor>0</rem:minor>
<rem:date>
<rem:year>2012</rem:year>
<rem:month>10</rem:month>
<rem:day>5</rem:day>
</rem:date>
</rem:version>
<rem:comments>
Ninguno</rem:comments>
<rem:level>1</rem:level>
<rem:number>3 </rem:number>
<rem:section
 oid = "SEC-0001">
<rem:name>
Enunciado</rem:name>
<rem:version>
<rem:major>1</rem:major>
<rem:minor>0</rem:minor>
<rem:date>
<rem:year>2012</rem:year>
<rem:month>9</rem:month>
<rem:day>30</rem:day>
</rem:date>
</rem:version>
<rem:comments>
Ninguno</rem:comments>
<rem:level>2</rem:level>
<rem:number>3.1 </rem:number>
<rem:paragraph
 oid = "PRG-0001">
<rem:name>
Contexto de Operacion </rem:name>
<rem:version>
<rem:major>1</rem:major>
<rem:minor>0</rem:minor>
<rem:date>
<rem:year>2012</rem:year>
<rem:month>9</rem:month>
<rem:day>30</rem:day>
</rem:date>
</rem:version>
<rem:authors stakeholders ="STK-0001 STK-0002 "/>
<rem:sources stakeholders ="STK-0003 "/>
<rem:comments>
Ninguno</rem:comments>
<rem:text>Se requiere una aplicación que controle los gastos de una persona. Para esto la persona debe crear una cuenta donde ingresara su salario y discriminarlo de acuerdo al número de pagos que recibe, sea de manera semestral, trimestral, bimensual, mensual, quincenal o semanal. Se requiere que sea tipo calendario para colocar en los días intermedios a los pagos la información de las obligaciones financieras que posee de la siguiente manera: se colocara en una fecha determinada, nombre de la obligación, valor a pagar, fecha de la obligación, fecha de alerta, hora de alerta, tipo de alerta. <br/>La aplicación descontara o aumentara del salario inicialmente ingresado el valor correspondiente al evento configurado en el calendario y de manera automática arrojara el valor a favor o en contra, con el fin de optimizar u organizar mis recursos y obtener un control específico frente a mis obligaciones. <br/>Además de esto podremos conocer el estado de las obligaciones (cumplida o descartada).<br/></rem:text>
</rem:paragraph>
</rem:section>
<rem:section
 oid = "SEC-0002">
<rem:name>
Necesidades </rem:name>
<rem:version>
<rem:major>1</rem:major>
<rem:minor>0</rem:minor>
<rem:date>
<rem:year>2012</rem:year>
<rem:month>9</rem:month>
<rem:day>30</rem:day>
</rem:date>
</rem:version>
<rem:comments>
Ninguno</rem:comments>
<rem:level>2</rem:level>
<rem:number>3.2 </rem:number>
<rem:objective
 oid = "OBJ-0009">
<rem:name>
Relacion de ingresos y Egresos</rem:name>
<rem:version>
<rem:major>1</rem:major>
<rem:minor>0</rem:minor>
<rem:date>
<rem:year>2012</rem:year>
<rem:month>10</rem:month>
<rem:day>5</rem:day>
</rem:date>
</rem:version>
<rem:authors stakeholders ="STK-0001 STK-0002 "/>
<rem:sources stakeholders ="STK-0003 "/>
<rem:comments>
Ninguno</rem:comments>
<rem:importance value = "IMV-0002"/>
<rem:urgency value = "URV-0002"/>
<rem:status value = "STV-0004"/>
<rem:stability value = "SBV-0004"/>
<rem:description>
Almacenar los datos ingresados por el  usuario, correspondientes a las obligaciones y/o necesidades financieras.</rem:description>
</rem:objective>
<rem:objective
 oid = "OBJ-0010">
<rem:name>
identificar obligaciones financiaras </rem:name>
<rem:version>
<rem:major>1</rem:major>
<rem:minor>0</rem:minor>
<rem:date>
<rem:year>2012</rem:year>
<rem:month>10</rem:month>
<rem:day>5</rem:day>
</rem:date>
</rem:version>
<rem:authors stakeholders ="STK-0001 STK-0002 "/>
<rem:sources stakeholders ="STK-0003 "/>
<rem:comments>
Ninguno</rem:comments>
<rem:importance value = "IMV-0002"/>
<rem:urgency value = "URV-0002"/>
<rem:status value = "STV-0004"/>
<rem:stability value = "SBV-0004"/>
<rem:description>
identificar obligaciones financiaras  para cubrilas a partir de los ingresos<br/><br/></rem:description>
</rem:objective>
<rem:objective
 oid = "OBJ-0011">
<rem:name>
Generar alarma</rem:name>
<rem:version>
<rem:major>1</rem:major>
<rem:minor>0</rem:minor>
<rem:date>
<rem:year>2012</rem:year>
<rem:month>10</rem:month>
<rem:day>5</rem:day>
</rem:date>
</rem:version>
<rem:authors stakeholders ="STK-0001 STK-0002 "/>
<rem:sources stakeholders ="STK-0003 "/>
<rem:comments>
Ninguno</rem:comments>
<rem:importance value = "IMV-0002"/>
<rem:urgency value = "URV-0003"/>
<rem:status value = "STV-0004"/>
<rem:stability value = "SBV-0004"/>
<rem:description>
Generar un aviso cuando se deba realizar el pago de una obligacion</rem:description>
</rem:objective>
<rem:objective
 oid = "OBJ-0012">
<rem:name>
Proyecion de gastos</rem:name>
<rem:version>
<rem:major>1</rem:major>
<rem:minor>0</rem:minor>
<rem:date>
<rem:year>2012</rem:year>
<rem:month>10</rem:month>
<rem:day>5</rem:day>
</rem:date>
</rem:version>
<rem:authors stakeholders ="STK-0001 STK-0002 "/>
<rem:sources stakeholders ="STK-0003 "/>
<rem:comments>
Ninguno</rem:comments>
<rem:importance value = "IMV-0003"/>
<rem:urgency value = "URV-0003"/>
<rem:status value = "STV-0004"/>
<rem:stability value = "SBV-0004"/>
<rem:description>
permitir al usuario realizar una planeacion  adecauda de sus gastos con el fin de clarificar sus finanzas para un determinado periodo.</rem:description>
</rem:objective>
<rem:objective
 oid = "OBJ-0013">
<rem:name>
Registros  de eventos</rem:name>
<rem:version>
<rem:major>1</rem:major>
<rem:minor>0</rem:minor>
<rem:date>
<rem:year>2012</rem:year>
<rem:month>10</rem:month>
<rem:day>5</rem:day>
</rem:date>
</rem:version>
<rem:authors stakeholders ="STK-0001 STK-0002 "/>
<rem:sources stakeholders ="STK-0003 "/>
<rem:comments>
Ninguno</rem:comments>
<rem:importance value = "IMV-0004"/>
<rem:urgency value = "URV-0004"/>
<rem:status value = "STV-0004"/>
<rem:stability value = "SBV-0003"/>
<rem:description>
almacenar los registros de cada evento con un mes de antelacion </rem:description>
</rem:objective>
</rem:section>
<rem:section
 oid = "SEC-0010">
<rem:name>
Caracteristicas</rem:name>
<rem:version>
<rem:major>1</rem:major>
<rem:minor>0</rem:minor>
<rem:date>
<rem:year>2012</rem:year>
<rem:month>10</rem:month>
<rem:day>5</rem:day>
</rem:date>
</rem:version>
<rem:comments>
Ninguno</rem:comments>
<rem:level>2</rem:level>
<rem:number>3.3 </rem:number>
<rem:paragraph
 oid = "PRG-0003">
<rem:name>
Lista de Caracteristicas</rem:name>
<rem:version>
<rem:major>1</rem:major>
<rem:minor>0</rem:minor>
<rem:date>
<rem:year>2012</rem:year>
<rem:month>10</rem:month>
<rem:day>6</rem:day>
</rem:date>
</rem:version>
<rem:authors stakeholders ="STK-0001 STK-0002 "/>
<rem:sources stakeholders ="STK-0003 "/>
<rem:comments>
Ninguno</rem:comments>
<rem:text>- Cuenta : <br/><br/>Administrar Usuario; el sistema permitira crear modificar y eliminar una cuenta<br/><br/>- Evento: <br/><br/>Detalle Evento :  el sistema permitira  crear actualizar, borrar , y consultar eventos.<br/><br/>Borrado automatico: pasado un mes se borraran todos los registos cumplidos hasta el momento.<br/><br/></rem:text>
</rem:paragraph>
</rem:section>
<rem:section
 oid = "SEC-0008">
<rem:name>
Prototipo</rem:name>
<rem:version>
<rem:major>1</rem:major>
<rem:minor>0</rem:minor>
<rem:date>
<rem:year>2012</rem:year>
<rem:month>9</rem:month>
<rem:day>30</rem:day>
</rem:date>
</rem:version>
<rem:comments>
Ninguno</rem:comments>
<rem:level>2</rem:level>
<rem:number>3.4 </rem:number>
<rem:graphicFile
 oid = "GRF-0003">
<rem:name>
Inicio</rem:name>
<rem:version>
<rem:major>1</rem:major>
<rem:minor>0</rem:minor>
<rem:date>
<rem:year>2012</rem:year>
<rem:month>10</rem:month>
<rem:day>6</rem:day>
</rem:date>
</rem:version>
<rem:authors stakeholders ="STK-0001 STK-0002 "/>
<rem:sources stakeholders ="STK-0003 "/>
<rem:comments>
Ninguno</rem:comments>
<rem:fileName>
<![CDATA[.\Diseño\Inicio.png]]>
</rem:fileName>
</rem:graphicFile>
<rem:graphicFile
 oid = "GRF-0004">
<rem:name>
configuracion de cuenta</rem:name>
<rem:version>
<rem:major>1</rem:major>
<rem:minor>0</rem:minor>
<rem:date>
<rem:year>2012</rem:year>
<rem:month>10</rem:month>
<rem:day>6</rem:day>
</rem:date>
</rem:version>
<rem:authors stakeholders ="STK-0001 STK-0002 "/>
<rem:sources stakeholders ="STK-0003 "/>
<rem:comments>
Ninguno</rem:comments>
<rem:fileName>
<![CDATA[.\Diseño\Configutacion de Cuenta.png]]>
</rem:fileName>
</rem:graphicFile>
<rem:graphicFile
 oid = "GRF-0005">
<rem:name>
Calendario Evento </rem:name>
<rem:version>
<rem:major>1</rem:major>
<rem:minor>0</rem:minor>
<rem:date>
<rem:year>2012</rem:year>
<rem:month>10</rem:month>
<rem:day>6</rem:day>
</rem:date>
</rem:version>
<rem:authors stakeholders ="STK-0001 STK-0002 "/>
<rem:sources stakeholders ="STK-0003 "/>
<rem:comments>
Ninguno</rem:comments>
<rem:fileName>
<![CDATA[.\Diseño\Calendario Evento.png]]>
</rem:fileName>
</rem:graphicFile>
<rem:graphicFile
 oid = "GRF-0006">
<rem:name>
Detalle Evento </rem:name>
<rem:version>
<rem:major>1</rem:major>
<rem:minor>0</rem:minor>
<rem:date>
<rem:year>2012</rem:year>
<rem:month>10</rem:month>
<rem:day>6</rem:day>
</rem:date>
</rem:version>
<rem:authors stakeholders ="STK-0001 STK-0002 "/>
<rem:sources stakeholders ="STK-0003 "/>
<rem:comments>
Ninguno</rem:comments>
<rem:fileName>
<![CDATA[.\Diseño\Detalle Evento.png]]>
</rem:fileName>
</rem:graphicFile>
<rem:graphicFile
 oid = "GRF-0007">
<rem:name>
Eventos Diarios</rem:name>
<rem:version>
<rem:major>1</rem:major>
<rem:minor>0</rem:minor>
<rem:date>
<rem:year>2012</rem:year>
<rem:month>10</rem:month>
<rem:day>6</rem:day>
</rem:date>
</rem:version>
<rem:authors stakeholders ="STK-0001 STK-0002 "/>
<rem:sources stakeholders ="STK-0003 "/>
<rem:comments>
Ninguno</rem:comments>
<rem:fileName>
<![CDATA[.\Diseño\Eventos Diarios.png]]>
</rem:fileName>
</rem:graphicFile>
<rem:graphicFile
 oid = "GRF-0008">
<rem:name>
Consulta de Evento</rem:name>
<rem:version>
<rem:major>1</rem:major>
<rem:minor>0</rem:minor>
<rem:date>
<rem:year>2012</rem:year>
<rem:month>10</rem:month>
<rem:day>6</rem:day>
</rem:date>
</rem:version>
<rem:authors stakeholders ="STK-0001 STK-0002 "/>
<rem:sources stakeholders ="STK-0003 "/>
<rem:comments>
Ninguno</rem:comments>
<rem:fileName>
<![CDATA[.\Diseño\Cunsulta de Eventos.png]]>
</rem:fileName>
</rem:graphicFile>
<rem:graphicFile
 oid = "GRF-0002">
<rem:name>
Prototipo General</rem:name>
<rem:version>
<rem:major>1</rem:major>
<rem:minor>0</rem:minor>
<rem:date>
<rem:year>2012</rem:year>
<rem:month>10</rem:month>
<rem:day>1</rem:day>
</rem:date>
</rem:version>
<rem:authors stakeholders ="STK-0001 STK-0002 "/>
<rem:sources stakeholders ="STK-0003 "/>
<rem:comments>
Ninguno</rem:comments>
<rem:fileName>
<![CDATA[.\Diseño\dibujo-2.png]]>
</rem:fileName>
</rem:graphicFile>
</rem:section>
</rem:section>
<rem:section
 oid = "SEC-0011">
<rem:name>
Requisitos</rem:name>
<rem:version>
<rem:major>1</rem:major>
<rem:minor>0</rem:minor>
<rem:date>
<rem:year>2012</rem:year>
<rem:month>10</rem:month>
<rem:day>5</rem:day>
</rem:date>
</rem:version>
<rem:comments>
Ninguno</rem:comments>
<rem:level>1</rem:level>
<rem:number>4 </rem:number>
<rem:section
 oid = "SEC-0003">
<rem:name>
Funcionales</rem:name>
<rem:version>
<rem:major>1</rem:major>
<rem:minor>0</rem:minor>
<rem:date>
<rem:year>2012</rem:year>
<rem:month>9</rem:month>
<rem:day>30</rem:day>
</rem:date>
</rem:version>
<rem:authors stakeholders ="STK-0001 STK-0002 "/>
<rem:sources stakeholders ="STK-0003 "/>
<rem:comments>
Ninguno</rem:comments>
<rem:level>2</rem:level>
<rem:number>4.1 </rem:number>
<rem:functionalRequirement
 oid = "FRQ-0001">
<rem:name>
Administrar Cuenta</rem:name>
<rem:version>
<rem:major>1</rem:major>
<rem:minor>0</rem:minor>
<rem:date>
<rem:year>2012</rem:year>
<rem:month>10</rem:month>
<rem:day>6</rem:day>
</rem:date>
</rem:version>
<rem:authors stakeholders ="STK-0001 STK-0002 "/>
<rem:sources stakeholders ="STK-0003 "/>
<rem:comments>
Ninguno</rem:comments>
<rem:importance value = "IMV-0002"/>
<rem:urgency value = "URV-0002"/>
<rem:status value = "STV-0004"/>
<rem:stability value = "SBV-0004"/>
<rem:description>
Asignar una cuenta para  para poder  hacer uso de las funcionalidades que presenta la aplicacion, ademas permitira editar y eliminar la cuenta</rem:description>
</rem:functionalRequirement>
<rem:functionalRequirement
 oid = "FRQ-0002">
<rem:name>
Realizar Calculos</rem:name>
<rem:version>
<rem:major>1</rem:major>
<rem:minor>0</rem:minor>
<rem:date>
<rem:year>2012</rem:year>
<rem:month>10</rem:month>
<rem:day>6</rem:day>
</rem:date>
</rem:version>
<rem:authors stakeholders ="STK-0001 STK-0002 "/>
<rem:sources stakeholders ="STK-0003 "/>
<rem:comments>
Ninguno</rem:comments>
<rem:importance value = "IMV-0003"/>
<rem:urgency value = "URV-0002"/>
<rem:status value = "STV-0004"/>
<rem:stability value = "SBV-0004"/>
<rem:description>
Calcular el valor disponible a partir de la frecuencia asignada al salario base </rem:description>
</rem:functionalRequirement>
<rem:functionalRequirement
 oid = "FRQ-0003">
<rem:name>
Generar Alerta </rem:name>
<rem:version>
<rem:major>1</rem:major>
<rem:minor>0</rem:minor>
<rem:date>
<rem:year>2012</rem:year>
<rem:month>10</rem:month>
<rem:day>6</rem:day>
</rem:date>
</rem:version>
<rem:authors stakeholders ="STK-0001 STK-0002 "/>
<rem:sources stakeholders ="STK-0003 "/>
<rem:comments>
Ninguno</rem:comments>
<rem:importance value = "IMV-0002"/>
<rem:urgency value = "URV-0003"/>
<rem:status value = "STV-0004"/>
<rem:stability value = "SBV-0004"/>
<rem:description>
Generar una alerta segun la programacion del evento </rem:description>
</rem:functionalRequirement>
<rem:functionalRequirement
 oid = "FRQ-0004">
<rem:name>
Administar Evento</rem:name>
<rem:version>
<rem:major>1</rem:major>
<rem:minor>0</rem:minor>
<rem:date>
<rem:year>2012</rem:year>
<rem:month>10</rem:month>
<rem:day>6</rem:day>
</rem:date>
</rem:version>
<rem:authors stakeholders ="STK-0001 STK-0002 "/>
<rem:sources stakeholders ="STK-0003 "/>
<rem:comments>
Ninguno</rem:comments>
<rem:importance value = "IMV-0002"/>
<rem:urgency value = "URV-0003"/>
<rem:status value = "STV-0004"/>
<rem:stability value = "SBV-0004"/>
<rem:description>
Permitir crear,editar y eliminar eventos</rem:description>
</rem:functionalRequirement>
<rem:functionalRequirement
 oid = "FRQ-0005">
<rem:name>
Estado de la Cuenta </rem:name>
<rem:version>
<rem:major>1</rem:major>
<rem:minor>0</rem:minor>
<rem:date>
<rem:year>2012</rem:year>
<rem:month>10</rem:month>
<rem:day>6</rem:day>
</rem:date>
</rem:version>
<rem:authors stakeholders ="STK-0001 STK-0002 "/>
<rem:sources stakeholders ="STK-0003 "/>
<rem:comments>
Ninguno</rem:comments>
<rem:importance value = "IMV-0003"/>
<rem:urgency value = "URV-0002"/>
<rem:status value = "STV-0004"/>
<rem:stability value = "SBV-0004"/>
<rem:description>
Calcular ingresos y egresos a partir de los eventos y posteriormente mostrar al usuario el estado de cuenta</rem:description>
</rem:functionalRequirement>
<rem:functionalRequirement
 oid = "FRQ-0006">
<rem:name>
Cosultar Eventos </rem:name>
<rem:version>
<rem:major>1</rem:major>
<rem:minor>0</rem:minor>
<rem:date>
<rem:year>2012</rem:year>
<rem:month>10</rem:month>
<rem:day>6</rem:day>
</rem:date>
</rem:version>
<rem:authors stakeholders ="STK-0001 STK-0002 "/>
<rem:sources stakeholders ="STK-0003 "/>
<rem:comments>
Ninguno</rem:comments>
<rem:importance value = "IMV-0004"/>
<rem:urgency value = "URV-0004"/>
<rem:status value = "STV-0004"/>
<rem:stability value = "SBV-0003"/>
<rem:description>
Mostrar registros de eventos vencidos</rem:description>
</rem:functionalRequirement>
</rem:section>
<rem:section
 oid = "SEC-0012">
<rem:name>
No Funcionales</rem:name>
<rem:version>
<rem:major>1</rem:major>
<rem:minor>0</rem:minor>
<rem:date>
<rem:year>2012</rem:year>
<rem:month>10</rem:month>
<rem:day>6</rem:day>
</rem:date>
</rem:version>
<rem:authors stakeholders ="STK-0001 STK-0002 "/>
<rem:sources stakeholders ="STK-0003 "/>
<rem:comments>
Ninguno</rem:comments>
<rem:level>2</rem:level>
<rem:number>4.2 </rem:number>
</rem:section>
<rem:section
 oid = "SEC-0013">
<rem:name>
De Informacion</rem:name>
<rem:version>
<rem:major>1</rem:major>
<rem:minor>0</rem:minor>
<rem:date>
<rem:year>2012</rem:year>
<rem:month>10</rem:month>
<rem:day>26</rem:day>
</rem:date>
</rem:version>
<rem:authors stakeholders ="STK-0001 STK-0002 "/>
<rem:sources stakeholders ="STK-0003 "/>
<rem:comments>
Ninguno</rem:comments>
<rem:level>2</rem:level>
<rem:number>4.3 </rem:number>
<rem:informationRequirement
 oid = "IRQ-0001">
<rem:name>
Datos de la cuenta</rem:name>
<rem:version>
<rem:major>1</rem:major>
<rem:minor>0</rem:minor>
<rem:date>
<rem:year>2012</rem:year>
<rem:month>10</rem:month>
<rem:day>26</rem:day>
</rem:date>
</rem:version>
<rem:authors stakeholders ="STK-0001 STK-0002 "/>
<rem:sources stakeholders ="STK-0003 "/>
<rem:comments>
Ninguno</rem:comments>
<rem:importance value = "IMV-0002"/>
<rem:urgency value = "URV-0002"/>
<rem:status value = "STV-0004"/>
<rem:stability value = "SBV-0004"/>
<rem:relevantConcept>
Usuario</rem:relevantConcept>
<rem:averageLifeTime>
<rem:value>6</rem:value>
<rem:timeUnit value = "TUV-0005"/>
</rem:averageLifeTime>
<rem:maximumLifeTime>
<rem:value>1</rem:value>
<rem:timeUnit value = "TUV-0002"/>
</rem:maximumLifeTime>
<rem:averageOcurrences><rem:tbd/>
</rem:averageOcurrences>
<rem:maximumOcurrences><rem:tbd/>
</rem:maximumOcurrences>
<rem:specificData oid = "DAT-0004">
<rem:description>
Nombre</rem:description>
<rem:comments>
Ninguno</rem:comments>
</rem:specificData>
<rem:specificData oid = "DAT-0001">
<rem:description>
Salario Base</rem:description>
<rem:comments>
Ninguno</rem:comments>
</rem:specificData>
<rem:specificData oid = "DAT-0002">
<rem:description>
Frecuencia de pago</rem:description>
<rem:comments>
Ninguno</rem:comments>
</rem:specificData>
<rem:specificData oid = "DAT-0005">
<rem:description>
Rangos</rem:description>
<rem:comments>
Periodo de dias entre pago y pago</rem:comments>
</rem:specificData>
</rem:informationRequirement>
<rem:informationRequirement
 oid = "IRQ-0003">
<rem:name>
Datos del evento</rem:name>
<rem:version>
<rem:major>1</rem:major>
<rem:minor>0</rem:minor>
<rem:date>
<rem:year>2012</rem:year>
<rem:month>10</rem:month>
<rem:day>26</rem:day>
</rem:date>
</rem:version>
<rem:authors stakeholders ="STK-0001 STK-0002 "/>
<rem:sources stakeholders ="STK-0003 "/>
<rem:comments>
Ninguno</rem:comments>
<rem:importance value = "IMV-0003"/>
<rem:urgency value = "URV-0003"/>
<rem:status value = "STV-0004"/>
<rem:stability value = "SBV-0004"/>
<rem:relevantConcept>
Datos de un evento</rem:relevantConcept>
<rem:averageLifeTime>
<rem:tbd/>
</rem:averageLifeTime>
<rem:maximumLifeTime>
<rem:tbd/>
</rem:maximumLifeTime>
<rem:averageOcurrences><rem:tbd/>
</rem:averageOcurrences>
<rem:maximumOcurrences><rem:tbd/>
</rem:maximumOcurrences>
</rem:informationRequirement>
<rem:informationRequirement
 oid = "IRQ-0002">
<rem:name>
Eventos Cumplidos</rem:name>
<rem:version>
<rem:major>1</rem:major>
<rem:minor>0</rem:minor>
<rem:date>
<rem:year>2012</rem:year>
<rem:month>10</rem:month>
<rem:day>26</rem:day>
</rem:date>
</rem:version>
<rem:authors stakeholders ="STK-0001 STK-0002 "/>
<rem:sources stakeholders ="STK-0003 "/>
<rem:comments>
Ninguno</rem:comments>
<rem:importance>
<rem:tbd/>
</rem:importance>
<rem:urgency>
<rem:tbd/>
</rem:urgency>
<rem:status>
<rem:tbd/>
</rem:status>
<rem:stability>
<rem:tbd/>
</rem:stability>
<rem:relevantConcept>
Eventos</rem:relevantConcept>
<rem:averageLifeTime>
<rem:tbd/>
</rem:averageLifeTime>
<rem:maximumLifeTime>
<rem:value>30</rem:value>
<rem:timeUnit value = "TUV-0008"/>
</rem:maximumLifeTime>
<rem:averageOcurrences><rem:tbd/>
</rem:averageOcurrences>
<rem:maximumOcurrences><rem:tbd/>
</rem:maximumOcurrences>
<rem:specificData oid = "DAT-0006">
<rem:description>
Nombre</rem:description>
<rem:comments>
Ninguno</rem:comments>
</rem:specificData>
<rem:specificData oid = "DAT-0003">
<rem:description>
Descripcion del evento</rem:description>
<rem:comments>
Ninguno</rem:comments>
</rem:specificData>
<rem:specificData oid = "DAT-0007">
<rem:description>
Fecha</rem:description>
<rem:comments>
Ninguno</rem:comments>
</rem:specificData>
</rem:informationRequirement>
</rem:section>
</rem:section>
<rem:section
 oid = "SEC-0014">
<rem:name>
Casos de Uso</rem:name>
<rem:version>
<rem:major>1</rem:major>
<rem:minor>0</rem:minor>
<rem:date>
<rem:year>2012</rem:year>
<rem:month>10</rem:month>
<rem:day>26</rem:day>
</rem:date>
</rem:version>
<rem:authors stakeholders ="STK-0001 STK-0002 "/>
<rem:sources stakeholders ="STK-0003 "/>
<rem:comments>
Ninguno</rem:comments>
<rem:level>1</rem:level>
<rem:number>5 </rem:number>
<rem:section
 oid = "SEC-0015">
<rem:name>
Actores</rem:name>
<rem:version>
<rem:major>1</rem:major>
<rem:minor>0</rem:minor>
<rem:date>
<rem:year>2012</rem:year>
<rem:month>10</rem:month>
<rem:day>26</rem:day>
</rem:date>
</rem:version>
<rem:authors stakeholders ="STK-0001 "/>
<rem:sources stakeholders ="STK-0003 "/>
<rem:comments>
Ninguno</rem:comments>
<rem:level>2</rem:level>
<rem:number>5.1 </rem:number>
<rem:actor
 oid = "ACT-0001">
<rem:name>
Usuario</rem:name>
<rem:version>
<rem:major>1</rem:major>
<rem:minor>0</rem:minor>
<rem:date>
<rem:year>2012</rem:year>
<rem:month>10</rem:month>
<rem:day>26</rem:day>
</rem:date>
</rem:version>
<rem:authors stakeholders ="STK-0001 STK-0002 "/>
<rem:sources stakeholders ="STK-0003 "/>
<rem:comments>
Ninguno</rem:comments>
<rem:actorRole>Persona encargada de todas las responsabilidades de los eventos (usuario operador del telefono movil)</rem:actorRole>
</rem:actor>
</rem:section>
<rem:section
 oid = "SEC-0016">
<rem:name>
Casos de Usos</rem:name>
<rem:version>
<rem:major>1</rem:major>
<rem:minor>0</rem:minor>
<rem:date>
<rem:year>2012</rem:year>
<rem:month>10</rem:month>
<rem:day>26</rem:day>
</rem:date>
</rem:version>
<rem:authors stakeholders ="STK-0001 STK-0002 "/>
<rem:sources stakeholders ="STK-0003 "/>
<rem:comments>
Ninguno</rem:comments>
<rem:level>2</rem:level>
<rem:number>5.2 </rem:number>
<rem:useCase
 oid = "UC-0001">
<rem:name>
Iniciar aplicacion</rem:name>
<rem:version>
<rem:major>1</rem:major>
<rem:minor>0</rem:minor>
<rem:date>
<rem:year>2012</rem:year>
<rem:month>10</rem:month>
<rem:day>26</rem:day>
</rem:date>
</rem:version>
<rem:authors stakeholders ="STK-0001 STK-0002 "/>
<rem:sources stakeholders ="STK-0003 "/>
<rem:comments>
Ninguno</rem:comments>
<rem:importance value = "IMV-0002"/>
<rem:urgency value = "URV-0002"/>
<rem:status value = "STV-0004"/>
<rem:stability value = "SBV-0004"/>
<rem:triggeringEvent>
El usuario ingresara en la aplicacion</rem:triggeringEvent>
<rem:precondition>
<rem:tbd/></rem:precondition>
<rem:postcondition>
La aplicacion sera iniciada</rem:postcondition>
<rem:frequency>
<rem:tbd/>
</rem:frequency>
<rem:step oid = "STP-0008">
<rem:number>1</rem:number>
<rem:systemAction>
<rem:description>
solicita el nombre de la cuenta</rem:description>
</rem:systemAction>
<rem:stepException oid = "STX-0002">
<rem:condition>
el usuario no tiene cuenta</rem:condition>
<rem:useCaseAction useCase = "UC-0003"/><rem:termination value = "TEV-0003"/>
<rem:comments>
Ninguno</rem:comments>
</rem:stepException>
<rem:comments>
Ninguno</rem:comments>
</rem:step>
<rem:step oid = "STP-0010">
<rem:number>2</rem:number>
<rem:actorAction actor = "ACT-0001">
<rem:description>
Ingresa el nombre de la cuenta</rem:description>
</rem:actorAction>
<rem:comments>
Ninguno</rem:comments>
</rem:step>
<rem:step oid = "STP-0011">
<rem:number>3</rem:number>
<rem:systemAction>
<rem:description>
valida el nombre de la cuenta</rem:description>
</rem:systemAction>
<rem:stepException oid = "STX-0004">
<rem:condition>
el nombre de la cuenta es incorrecto</rem:condition>
<rem:systemAction>
<rem:description>
mostrara un mensaje al usuario indicando nombre de cuenta incorrecto</rem:description>
</rem:systemAction>
<rem:termination value = "TEV-0003"/>
<rem:comments>
Ninguno</rem:comments>
</rem:stepException>
<rem:comments>
Ninguno</rem:comments>
</rem:step>
<rem:step oid = "STP-0009">
<rem:number>4</rem:number>
<rem:systemAction>
<rem:description>
cargara la cuenta</rem:description>
</rem:systemAction>
<rem:comments>
Ninguno</rem:comments>
</rem:step>
</rem:useCase>
<rem:useCase
 oid = "UC-0004">
<rem:name>
Crear Eventos</rem:name>
<rem:version>
<rem:major>1</rem:major>
<rem:minor>0</rem:minor>
<rem:date>
<rem:year>2012</rem:year>
<rem:month>10</rem:month>
<rem:day>26</rem:day>
</rem:date>
</rem:version>
<rem:authors stakeholders ="STK-0001 STK-0002 "/>
<rem:sources stakeholders ="STK-0003 "/>
<rem:comments>
Ninguno</rem:comments>
<rem:importance value = "IMV-0002"/>
<rem:urgency value = "URV-0002"/>
<rem:status value = "STV-0004"/>
<rem:stability value = "SBV-0004"/>
<rem:triggeringEvent>
El usuario ingresa un evento al calendario</rem:triggeringEvent>
<rem:precondition>
<rem:tbd/></rem:precondition>
<rem:postcondition>
El sistema calcula el saldo de la cuenta</rem:postcondition>
<rem:frequency>
<rem:tbd/>
</rem:frequency>
<rem:step oid = "STP-0013">
<rem:number>1</rem:number>
<rem:actorAction actor = "ACT-0001">
<rem:description>
solicita al sistema la creacion de un evento</rem:description>
</rem:actorAction>
<rem:comments>
Ninguno</rem:comments>
</rem:step>
</rem:useCase>
<rem:useCase
 oid = "UC-0002">
<rem:name>
Asignacion de salario a periodo en el calendario</rem:name>
<rem:version>
<rem:major>1</rem:major>
<rem:minor>0</rem:minor>
<rem:date>
<rem:year>2012</rem:year>
<rem:month>10</rem:month>
<rem:day>26</rem:day>
</rem:date>
</rem:version>
<rem:authors stakeholders ="STK-0001 STK-0002 "/>
<rem:sources stakeholders ="STK-0003 "/>
<rem:comments>
Ninguno</rem:comments>
<rem:importance value = "IMV-0002"/>
<rem:urgency value = "URV-0002"/>
<rem:status value = "STV-0004"/>
<rem:stability value = "SBV-0004"/>
<rem:triggeringEvent>
El sistema asignara a un periodo determinado el saldo partir del salario base.</rem:triggeringEvent>
<rem:precondition>
<rem:tbd/></rem:precondition>
<rem:postcondition>
Se mostrara el calendario</rem:postcondition>
<rem:frequency>
<rem:tbd/>
</rem:frequency>
</rem:useCase>
<rem:useCase
 oid = "UC-0003">
<rem:name>
Crear cuenta</rem:name>
<rem:version>
<rem:major>1</rem:major>
<rem:minor>0</rem:minor>
<rem:date>
<rem:year>2012</rem:year>
<rem:month>10</rem:month>
<rem:day>26</rem:day>
</rem:date>
</rem:version>
<rem:authors stakeholders ="STK-0001 STK-0002 "/>
<rem:sources stakeholders ="STK-0003 "/>
<rem:comments>
Ninguno</rem:comments>
<rem:importance value = "IMV-0002"/>
<rem:urgency value = "URV-0002"/>
<rem:status value = "STV-0004"/>
<rem:stability value = "SBV-0004"/>
<rem:triggeringEvent>
El usuario ingresa los datos correspondientes a la cuenta (Salario, Frecuencia de pago, Rango(s))</rem:triggeringEvent>
<rem:precondition>
<rem:tbd/></rem:precondition>
<rem:postcondition>
<rem:tbd/></rem:postcondition>
<rem:frequency>
<rem:tbd/>
</rem:frequency>
</rem:useCase>
<rem:useCase
 oid = "UC-0006">
<rem:name>
Calcular estado de cuenta</rem:name>
<rem:version>
<rem:major>1</rem:major>
<rem:minor>0</rem:minor>
<rem:date>
<rem:year>2012</rem:year>
<rem:month>10</rem:month>
<rem:day>26</rem:day>
</rem:date>
</rem:version>
<rem:authors stakeholders ="STK-0001 STK-0002 "/>
<rem:sources stakeholders ="STK-0003 "/>
<rem:comments>
Ninguno</rem:comments>
<rem:importance value = "IMV-0002"/>
<rem:urgency value = "URV-0002"/>
<rem:status value = "STV-0004"/>
<rem:stability value = "SBV-0004"/>
<rem:triggeringEvent>
El sistema calcula el saldo de la cuenta a partir de los eventos creados</rem:triggeringEvent>
<rem:precondition>
<rem:tbd/></rem:precondition>
<rem:postcondition>
<rem:tbd/></rem:postcondition>
<rem:frequency>
<rem:tbd/>
</rem:frequency>
</rem:useCase>
</rem:section>
</rem:section>
<rem:section
 oid = "SEC-0007">
<rem:name>
Diagrama de Flujo</rem:name>
<rem:version>
<rem:major>1</rem:major>
<rem:minor>0</rem:minor>
<rem:date>
<rem:year>2012</rem:year>
<rem:month>9</rem:month>
<rem:day>30</rem:day>
</rem:date>
</rem:version>
<rem:comments>
Ninguno</rem:comments>
<rem:level>1</rem:level>
<rem:number>6 </rem:number>
<rem:graphicFile
 oid = "GRF-0001">
<rem:name>
Diagrama de flujo</rem:name>
<rem:version>
<rem:major>1</rem:major>
<rem:minor>0</rem:minor>
<rem:date>
<rem:year>2012</rem:year>
<rem:month>9</rem:month>
<rem:day>30</rem:day>
</rem:date>
</rem:version>
<rem:authors stakeholders ="STK-0001 STK-0002 "/>
<rem:comments>
Ninguno</rem:comments>
<rem:fileName>
<![CDATA[.\Diagrama de flujo\diagrama de flujo1.png]]>
</rem:fileName>
</rem:graphicFile>
</rem:section>
<rem:section
 oid = "SEC-0004">
<rem:name>
Glosario</rem:name>
<rem:version>
<rem:major>1</rem:major>
<rem:minor>0</rem:minor>
<rem:date>
<rem:year>2012</rem:year>
<rem:month>9</rem:month>
<rem:day>30</rem:day>
</rem:date>
</rem:version>
<rem:comments>
Ninguno</rem:comments>
<rem:level>1</rem:level>
<rem:number>7 </rem:number>
</rem:section>
</rem:c_requirementsSpecification>
<rem:d_requirementsSpecification oid = "DRS-0002">
<rem:name>Documento de Análisis del Sistema</rem:name>
<rem:version>
<rem:major>1</rem:major>
<rem:minor>0</rem:minor>
<rem:date>
<rem:year>2012</rem:year>
<rem:month>9</rem:month>
<rem:day>30</rem:day>
</rem:date>
</rem:version>
<rem:comments>
Ninguno
</rem:comments>
</rem:d_requirementsSpecification>
<rem:defectsSpecification oid = "DFS-0003">
<rem:name>Registro de Conflictos y Defectos</rem:name>
<rem:version>
<rem:major>1</rem:major>
<rem:minor>0</rem:minor>
<rem:date>
<rem:year>2012</rem:year>
<rem:month>9</rem:month>
<rem:day>30</rem:day>
</rem:date>
</rem:version>
<rem:comments>
Ninguno
</rem:comments>
</rem:defectsSpecification>
<rem:changeRequestsSpecification oid = "CHS-0004">
<rem:name>Registro de Peticiones de Cambio</rem:name>
<rem:version>
<rem:major>1</rem:major>
<rem:minor>0</rem:minor>
<rem:date>
<rem:year>2012</rem:year>
<rem:month>9</rem:month>
<rem:day>30</rem:day>
</rem:date>
</rem:version>
<rem:comments>
Ninguno
</rem:comments>
</rem:changeRequestsSpecification>
<rem:predefinedValueTypes>
<rem:predefinedValueType
 oid = "PVT-0001">
<rem:name>
Real</rem:name>
<rem:version>
<rem:major>1</rem:major>
<rem:minor>0</rem:minor>
<rem:date>
<rem:year>2000</rem:year>
<rem:month>10</rem:month>
<rem:day>30</rem:day>
</rem:date>
</rem:version>
<rem:comments>
Predefined OCL type</rem:comments>
<rem:description>
Real numbers</rem:description>
<rem:definition>
(null)
</rem:definition>
</rem:predefinedValueType>
<rem:predefinedValueType
 oid = "PVT-0002">
<rem:name>
Integer</rem:name>
<rem:version>
<rem:major>1</rem:major>
<rem:minor>0</rem:minor>
<rem:date>
<rem:year>2000</rem:year>
<rem:month>10</rem:month>
<rem:day>30</rem:day>
</rem:date>
</rem:version>
<rem:comments>
Predefined OCL type</rem:comments>
<rem:description>
Integer numbers</rem:description>
<rem:definition>
(null)
</rem:definition>
</rem:predefinedValueType>
<rem:predefinedValueType
 oid = "PVT-0003">
<rem:name>
Natural</rem:name>
<rem:version>
<rem:major>1</rem:major>
<rem:minor>0</rem:minor>
<rem:date>
<rem:year>2000</rem:year>
<rem:month>10</rem:month>
<rem:day>30</rem:day>
</rem:date>
</rem:version>
<rem:comments>
Predefined OCL type</rem:comments>
<rem:description>
Natural numbers</rem:description>
<rem:definition>
(null)
</rem:definition>
</rem:predefinedValueType>
<rem:predefinedValueType
 oid = "PVT-0004">
<rem:name>
String</rem:name>
<rem:version>
<rem:major>1</rem:major>
<rem:minor>0</rem:minor>
<rem:date>
<rem:year>2000</rem:year>
<rem:month>10</rem:month>
<rem:day>30</rem:day>
</rem:date>
</rem:version>
<rem:comments>
Predefined OCL type</rem:comments>
<rem:description>
Alphanumeric strings</rem:description>
<rem:definition>
(null)
</rem:definition>
</rem:predefinedValueType>
<rem:predefinedValueType
 oid = "PVT-0005">
<rem:name>
Date</rem:name>
<rem:version>
<rem:major>1</rem:major>
<rem:minor>0</rem:minor>
<rem:date>
<rem:year>2000</rem:year>
<rem:month>10</rem:month>
<rem:day>30</rem:day>
</rem:date>
</rem:version>
<rem:comments>
Predefined OCL type (non-standard)</rem:comments>
<rem:description>
Dates</rem:description>
<rem:definition>
(null)
</rem:definition>
</rem:predefinedValueType>
<rem:predefinedValueType
 oid = "PVT-0006">
<rem:name>
Time</rem:name>
<rem:version>
<rem:major>1</rem:major>
<rem:minor>0</rem:minor>
<rem:date>
<rem:year>2000</rem:year>
<rem:month>10</rem:month>
<rem:day>30</rem:day>
</rem:date>
</rem:version>
<rem:comments>
Predefined OCL type (non-standard)</rem:comments>
<rem:description>
Hour:minutes:seconds</rem:description>
<rem:definition>
(null)
</rem:definition>
</rem:predefinedValueType>
</rem:predefinedValueTypes>
<rem:predefinedValues>
<rem:changeRequestStatusValue oid = "CRV-0001">
<rem:name>PD</rem:name>
</rem:changeRequestStatusValue>
<rem:changeRequestStatusValue oid = "CRV-0002">
<rem:name>pendiente de análisis</rem:name>
</rem:changeRequestStatusValue>
<rem:changeRequestStatusValue oid = "CRV-0003">
<rem:name>pendiente de aprobar/rechazar</rem:name>
</rem:changeRequestStatusValue>
<rem:changeRequestStatusValue oid = "CRV-0004">
<rem:name>pendiente de realización</rem:name>
</rem:changeRequestStatusValue>
<rem:changeRequestStatusValue oid = "CRV-0005">
<rem:name>verificado</rem:name>
</rem:changeRequestStatusValue>
<rem:changeRequestStatusValue oid = "CRV-0006">
<rem:name>rechazado</rem:name>
</rem:changeRequestStatusValue>
<rem:conflictStatusValue oid = "CSV-0001">
<rem:name>PD</rem:name>
</rem:conflictStatusValue>
<rem:conflictStatusValue oid = "CSV-0002">
<rem:name>no resuelto</rem:name>
</rem:conflictStatusValue>
<rem:conflictStatusValue oid = "CSV-0003">
<rem:name>en proceso de negociación</rem:name>
</rem:conflictStatusValue>
<rem:conflictStatusValue oid = "CSV-0004">
<rem:name>resuelto</rem:name>
</rem:conflictStatusValue>
<rem:defectStatusValue oid = "DSV-0001">
<rem:name>PD</rem:name>
</rem:defectStatusValue>
<rem:defectStatusValue oid = "DSV-0002">
<rem:name>no eliminado</rem:name>
</rem:defectStatusValue>
<rem:defectStatusValue oid = "DSV-0003">
<rem:name>en proceso de negociación</rem:name>
</rem:defectStatusValue>
<rem:defectStatusValue oid = "DSV-0004">
<rem:name>eliminado</rem:name>
</rem:defectStatusValue>
<rem:defectTypeValue oid = "DTV-0003">
<rem:name>No necesidad</rem:name>
<rem:description>
<![CDATA[El requisito o requisitos no son necesarios porque no contribuyen a satisfacer ninguna necesidad de clientes o usuarios]]>
</rem:description>
</rem:defectTypeValue>
<rem:defectTypeValue oid = "DTV-0004">
<rem:name>Incomprensibilidad</rem:name>
<rem:description>
<![CDATA[El requisito o requisitos no pueden ser entendidos por algún lector]]>
</rem:description>
</rem:defectTypeValue>
<rem:defectTypeValue oid = "DTV-0005">
<rem:name>No verificabilidad</rem:name>
<rem:description>
<![CDATA[No se puede comprobar que el sistema satisface el requisito o requisitos]]>
</rem:description>
</rem:defectTypeValue>
<rem:defectTypeValue oid = "DTV-0002">
<rem:name>Ambigüedad</rem:name>
<rem:description>
<![CDATA[El requisito o requisitos, aunque comprensibles, tienen más de una interpretación posible]]>
</rem:description>
</rem:defectTypeValue>
<rem:defectTypeValue oid = "DTV-0001">
<rem:name>PD</rem:name>
<rem:description>
<![CDATA[Por Determinar]]>
</rem:description>
</rem:defectTypeValue>
<rem:defectTypeValue oid = "DTV-0007">
<rem:name>No implementabilidad</rem:name>
<rem:description>
<![CDATA[El requisito o requisitos no pueden ser implementados con la tecnología actual o dentro de un coste razonable]]>
</rem:description>
</rem:defectTypeValue>
<rem:defectTypeValue oid = "DTV-0008">
<rem:name>Verbosidad excesiva</rem:name>
<rem:description>
<![CDATA[El requisito o requisitos pueden expresarse de forma más concisa sin alterar su significado]]>
</rem:description>
</rem:defectTypeValue>
<rem:defectTypeValue oid = "DTV-0006">
<rem:name>Inconsistencia</rem:name>
<rem:description>
<![CDATA[El requisito o requisitos no son consistentes, es decir, presentan contradicciones internas o entre varios]]>
</rem:description>
</rem:defectTypeValue>
<rem:defectTypeValue oid = "DTV-0009">
<rem:name>Dependiente del diseño</rem:name>
<rem:description>
<![CDATA[El requisito o requisitos incluyen elementos dependientes del diseño del sistema]]>
</rem:description>
</rem:defectTypeValue>
<rem:defectTypeValue oid = "DTV-0010">
<rem:name>Redundancia</rem:name>
<rem:description>
<![CDATA[El requisito o requisitos son redundantes o contienen elementos redundantes]]>
</rem:description>
</rem:defectTypeValue>
<rem:defectTypeValue oid = "DTV-0011">
<rem:name>Imprecisión</rem:name>
<rem:description>
<![CDATA[El requisito o requisitos no se expresan de forma precisa, es decir, usando cantidades numéricas siempre que sea posible con el nivel adecuado de precisión]]>
</rem:description>
</rem:defectTypeValue>
<rem:defectTypeValue oid = "DTV-0012">
<rem:name>Incompleción</rem:name>
<rem:description>
<![CDATA[El requisito o requisitos no describen todo lo que el sistema se supone que deberá hacer, no describen las respuestas del sistema a todas las posibles situaciones o incluyen elementos por determinar (PD)]]>
</rem:description>
</rem:defectTypeValue>
<rem:defectTypeValue oid = "DTV-0013">
<rem:name>Prioridad no establecida</rem:name>
<rem:description>
<![CDATA[El requisito o requisitos no tienen establecida su prioridad, es decir, su importancia y su urgencia]]>
</rem:description>
</rem:defectTypeValue>
<rem:defectTypeValue oid = "DTV-0014">
<rem:name>Estabilidad no establecida</rem:name>
<rem:description>
<![CDATA[El requisito o requisitos no tienen estimada su estabilidad]]>
</rem:description>
</rem:defectTypeValue>
<rem:defectTypeValue oid = "DTV-0015">
<rem:name>Nivel incorrecto de detalle</rem:name>
<rem:description>
<![CDATA[El requisito o requisitos no están expresados con el nivel adecuado de detalle, es decir, son demasiado abstractos o demasiado detallados]]>
</rem:description>
</rem:defectTypeValue>
<rem:defectTypeValue oid = "DTV-0016">
<rem:name>No rastreabilidad</rem:name>
<rem:description>
<![CDATA[El requisito o requisitos no están trazados hacia sus orígenes, bien requisitos de nivel superior (objetivos), bien clientes y usuarios]]>
</rem:description>
</rem:defectTypeValue>
<rem:defectTypeValue oid = "DTV-0017">
<rem:name>Organización incorrecta</rem:name>
<rem:description>
<![CDATA[El requisito o requisitos no están organizados correctamente según la normativa aplicada o el documento no contiene las secciones obligatorias]]>
</rem:description>
</rem:defectTypeValue>
<rem:defectTypeValue oid = "DTV-0023">
<rem:name>Otro</rem:name>
<rem:description>
<![CDATA[El requisito o requisitos presentan otro tipo de defecto]]>
</rem:description>
</rem:defectTypeValue>
<rem:importanceValue oid = "IMV-0001">
<rem:name>PD</rem:name>
</rem:importanceValue>
<rem:importanceValue oid = "IMV-0002">
<rem:name>vital</rem:name>
</rem:importanceValue>
<rem:importanceValue oid = "IMV-0003">
<rem:name>importante</rem:name>
</rem:importanceValue>
<rem:importanceValue oid = "IMV-0004">
<rem:name>quedaría bien</rem:name>
</rem:importanceValue>
<rem:stabilityValue oid = "SBV-0001">
<rem:name>PD</rem:name>
</rem:stabilityValue>
<rem:stabilityValue oid = "SBV-0002">
<rem:name>baja</rem:name>
</rem:stabilityValue>
<rem:stabilityValue oid = "SBV-0003">
<rem:name>media</rem:name>
</rem:stabilityValue>
<rem:stabilityValue oid = "SBV-0004">
<rem:name>alta</rem:name>
</rem:stabilityValue>
<rem:statusValue oid = "STV-0001">
<rem:name>PD</rem:name>
</rem:statusValue>
<rem:statusValue oid = "STV-0002">
<rem:name>en construcción</rem:name>
</rem:statusValue>
<rem:statusValue oid = "STV-0003">
<rem:name>pendiente de verificación</rem:name>
</rem:statusValue>
<rem:statusValue oid = "STV-0004">
<rem:name>pendiente de validación</rem:name>
</rem:statusValue>
<rem:statusValue oid = "STV-0005">
<rem:name>validado</rem:name>
</rem:statusValue>
<rem:terminationValue oid = "TEV-0001">
<rem:name>PD</rem:name>
</rem:terminationValue>
<rem:terminationValue oid = "TEV-0002">
<rem:name>continúa</rem:name>
</rem:terminationValue>
<rem:terminationValue oid = "TEV-0003">
<rem:name>queda sin efecto</rem:name>
</rem:terminationValue>
<rem:timeUnitValue oid = "TUV-0001">
<rem:name>PD</rem:name>
</rem:timeUnitValue>
<rem:timeUnitValue oid = "TUV-0002">
<rem:name>año(s)</rem:name>
</rem:timeUnitValue>
<rem:timeUnitValue oid = "TUV-0005">
<rem:name>mes(es)</rem:name>
</rem:timeUnitValue>
<rem:timeUnitValue oid = "TUV-0007">
<rem:name>semana(s)</rem:name>
</rem:timeUnitValue>
<rem:timeUnitValue oid = "TUV-0008">
<rem:name>día(s)</rem:name>
</rem:timeUnitValue>
<rem:timeUnitValue oid = "TUV-0009">
<rem:name>hora(s)</rem:name>
</rem:timeUnitValue>
<rem:timeUnitValue oid = "TUV-0010">
<rem:name>minuto(s)</rem:name>
</rem:timeUnitValue>
<rem:timeUnitValue oid = "TUV-0011">
<rem:name>segundo(s)</rem:name>
</rem:timeUnitValue>
<rem:timeUnitValue oid = "TUV-0012">
<rem:name>décima(s) de segundo</rem:name>
</rem:timeUnitValue>
<rem:timeUnitValue oid = "TUV-0013">
<rem:name>centésima(s) de segundo</rem:name>
</rem:timeUnitValue>
<rem:timeUnitValue oid = "TUV-0014">
<rem:name>milisegundo(s)</rem:name>
</rem:timeUnitValue>
<rem:urgencyValue oid = "URV-0001">
<rem:name>PD</rem:name>
</rem:urgencyValue>
<rem:urgencyValue oid = "URV-0002">
<rem:name>inmediatamente</rem:name>
</rem:urgencyValue>
<rem:urgencyValue oid = "URV-0003">
<rem:name>hay presión</rem:name>
</rem:urgencyValue>
<rem:urgencyValue oid = "URV-0004">
<rem:name>puede esperar</rem:name>
</rem:urgencyValue>
</rem:predefinedValues>
</rem:requirementsProject>
